infer_rvc_python/__init__.py
infer_rvc_python/main.py
infer_rvc_python/root_pipe.py
infer_rvc_python/lib/__init__.py
infer_rvc_python/lib/audio.py
infer_rvc_python/lib/log_config.py
infer_rvc_python/lib/rmvpe.py
infer_rvc_python/lib/infer_pack/__init__.py
infer_rvc_python/lib/infer_pack/attentions.py
infer_rvc_python/lib/infer_pack/commons.py
infer_rvc_python/lib/infer_pack/models.py
infer_rvc_python/lib/infer_pack/modules.py
infer_rvc_python/lib/infer_pack/transforms.py
infer_rvc_python-1.2.0.dist-info/licenses/LICENSE
infer_rvc_python-1.2.0.dist-info/METADATA
infer_rvc_python-1.2.0.dist-info/WHEEL
infer_rvc_python-1.2.0.dist-info/top_level.txt
infer_rvc_python-1.2.0.dist-info/RECORD
