Metadata-Version: 2.4
Name: infer_rvc_python
Version: 1.2.0
Summary: Python wrapper for fast inference with rvc
Home-page: https://github.com/R3gm/infer_rvc_python
Author: R3gm
License: MIT
Requires-Python: >=3.10
License-File: LICENSE
Requires-Dist: torch
Requires-Dist: torchaudio
Requires-Dist: gradio
Requires-Dist: praat-parselmouth>=0.4.3
Requires-Dist: pyworld==0.3.2
Requires-Dist: faiss-cpu==1.7.3
Requires-Dist: torchcrepe==0.0.20
Requires-Dist: ffmpeg-python>=0.2.0
Requires-Dist: fairseq==0.12.2
Requires-Dist: typeguard==4.2.0
Requires-Dist: soundfile
Requires-Dist: librosa
Requires-Dist: numpy
Provides-Extra: all
Requires-Dist: scipy; extra == "all"
Requires-Dist: numba==0.56.4; extra == "all"
Requires-Dist: edge-tts; extra == "all"
Dynamic: author
Dynamic: description
Dynamic: description-content-type
Dynamic: home-page
Dynamic: license
Dynamic: license-file
Dynamic: provides-extra
Dynamic: requires-dist
Dynamic: requires-python
Dynamic: summary
